pysegd/__init__.py
pysegd/blockdecoders.py
pysegd/control.py
pysegd/decoding.py
pysegd/headerfields.py
pysegd/readsegd30.py
pysegd/segddecim.py
pysegd/segdfile.py
pysegd/typedecoders.py
pysegd-4.0.1.data/scripts/readsegd30.py
pysegd-4.0.1.data/scripts/segddecim.py
pysegd-4.0.1.dist-info/LICENSE
pysegd-4.0.1.dist-info/METADATA
pysegd-4.0.1.dist-info/WHEEL
pysegd-4.0.1.dist-info/top_level.txt
pysegd-4.0.1.dist-info/RECORD
