Metadata-Version: 2.1
Name: pysegd
Version: 4.0.1
Home-page: 
Classifier: Programming Language :: Python :: 3
Classifier: Operating System :: POSIX :: Linux
Classifier: Operating System :: Microsoft :: Windows
Requires-Python: >=3.7
License-File: LICENSE
Requires-Dist: numpy
Requires-Dist: pytest
Requires-Dist: scipy
